pvblocks_io_rera/__init__.py
pvblocks_io_rera/__main__.py
pvblocks_io_rera/constants.py
pvblocks_io_rera/exceptions.py
pvblocks_io_rera/pvblocks_system.py
pvblocks_io_rera-0.0.1.dist-info/LICENSE
pvblocks_io_rera-0.0.1.dist-info/METADATA
pvblocks_io_rera-0.0.1.dist-info/WHEEL
pvblocks_io_rera-0.0.1.dist-info/top_level.txt
pvblocks_io_rera-0.0.1.dist-info/RECORD
