Metadata-Version: 2.1
Name: pvblocks_io_rera
Version: 0.0.1
Summary: Python package to directly control pvblocks modules
Author-email: Erik Haverkamp <erik@rera.nl>
Project-URL: Homepage, https://github.com/rerasolutions/pvblocks-python
Classifier: Programming Language :: Python :: 3
Classifier: License :: OSI Approved :: MIT License
Classifier: Operating System :: OS Independent
Requires-Python: >=3.8
License-File: LICENSE
